pdlsts/__init__.py
pdlsts-0.0.1.dist-info/licenses/LICENSE
pdlsts-0.0.1.dist-info/METADATA
pdlsts-0.0.1.dist-info/WHEEL
pdlsts-0.0.1.dist-info/top_level.txt
pdlsts-0.0.1.dist-info/RECORD
