Metadata-Version: 2.4
Name: pdlsts
Version: 0.0.1
Summary: Python Package for Santec Polarization Dependent Loss Swept Test System
Author: Santec Holdings Corporation
License-Expression: MIT
Requires-Python: >=3.7
License-File: LICENSE
Dynamic: license-file
